{
  "/home/jion1/securify/smart_contract_source_code/22902.sol:BuildingStatus": {
    "results": {
      "DAO": {
        "violations": [],
        "warnings": [],
        "safe": [],
        "conflicts": []
      },
      "DAOConstantGas": {
        "violations": [],
        "warnings": [],
        "safe": [],
        "conflicts": []
      },
      "LockedEther": {
        "violations": [],
        "warnings": [],
        "safe": [],
        "conflicts": [
          208
        ]
      },
      "MissingInputValidation": {
        "violations": [],
        "warnings": [
          183,
          200,
          210,
          213,
          262,
          266,
          271
        ],
        "safe": [],
        "conflicts": []
      },
      "TODAmount": {
        "violations": [],
        "warnings": [],
        "safe": [],
        "conflicts": []
      },
      "TODReceiver": {
        "violations": [],
        "warnings": [],
        "safe": [],
        "conflicts": []
      },
      "UnhandledException": {
        "violations": [],
        "warnings": [],
        "safe": [],
        "conflicts": []
      },
      "UnrestrictedEtherFlow": {
        "violations": [],
        "warnings": [],
        "safe": [],
        "conflicts": []
      },
      "UnrestrictedWrite": {
        "violations": [],
        "warnings": [],
        "safe": [],
        "conflicts": [
          203,
          267,
          272,
          273,
          274,
          275,
          276
        ]
      }
    },
    "securifyErrors": {
      "errors": []
    }
  },
  "/home/jion1/securify/smart_contract_source_code/22902.sol:ConvertQuote": {
    "results": {
      "DAO": {
        "violations": [],
        "warnings": [],
        "safe": [
          126
        ],
        "conflicts": []
      },
      "DAOConstantGas": {
        "violations": [],
        "warnings": [
          488
        ],
        "safe": [],
        "conflicts": []
      },
      "LockedEther": {
        "violations": [],
        "warnings": [
          634
        ],
        "safe": [],
        "conflicts": []
      },
      "MissingInputValidation": {
        "violations": [],
        "warnings": [],
        "safe": [],
        "conflicts": []
      },
      "TODAmount": {
        "violations": [
          488
        ],
        "warnings": [],
        "safe": [
          126
        ],
        "conflicts": []
      },
      "TODReceiver": {
        "violations": [],
        "warnings": [
          488
        ],
        "safe": [
          126
        ],
        "conflicts": []
      },
      "UnhandledException": {
        "violations": [],
        "warnings": [
          56,
          57,
          111,
          124,
          126,
          130,
          136,
          488,
          642
        ],
        "safe": [],
        "conflicts": []
      },
      "UnrestrictedEtherFlow": {
        "violations": [],
        "warnings": [
          56,
          57,
          111,
          124,
          130,
          136,
          488,
          642
        ],
        "safe": [
          126
        ],
        "conflicts": []
      },
      "UnrestrictedWrite": {
        "violations": [
          57,
          611,
          620,
          624,
          634
        ],
        "warnings": [],
        "safe": [],
        "conflicts": [
          57,
          72,
          77,
          82,
          87,
          92,
          96,
          100,
          203,
          460,
          470,
          481,
          582,
          584,
          591,
          596,
          601,
          634
        ]
      }
    },
    "securifyErrors": {
      "errors": []
    }
  },
  "/home/jion1/securify/smart_contract_source_code/22902.sol:Crowdsale": {
    "results": {
      "DAO": {
        "violations": [],
        "warnings": [],
        "safe": [],
        "conflicts": []
      },
      "DAOConstantGas": {
        "violations": [
          1345
        ],
        "warnings": [
          1157,
          1215,
          1227,
          1357
        ],
        "safe": [],
        "conflicts": []
      },
      "LockedEther": {
        "violations": [],
        "warnings": [
          950
        ],
        "safe": [],
        "conflicts": []
      },
      "MissingInputValidation": {
        "violations": [],
        "warnings": [],
        "safe": [],
        "conflicts": []
      },
      "TODAmount": {
        "violations": [
          1357
        ],
        "warnings": [
          1345
        ],
        "safe": [
          1157
        ],
        "conflicts": [
          1215,
          1227
        ]
      },
      "TODReceiver": {
        "violations": [
          1357
        ],
        "warnings": [
          1157,
          1345
        ],
        "safe": [],
        "conflicts": [
          1215,
          1227
        ]
      },
      "UnhandledException": {
        "violations": [],
        "warnings": [
          1027,
          1157,
          1166,
          1175,
          1180,
          1215,
          1218,
          1227,
          1269,
          1273,
          1277,
          1281,
          1292,
          1296,
          1298,
          1300,
          1315,
          1316,
          1318,
          1320,
          1332,
          1341,
          1344,
          1345,
          1357,
          1358,
          1371,
          1382,
          1402,
          1414,
          1423,
          1424,
          1425,
          1427,
          1436,
          1437,
          1438,
          1439
        ],
        "safe": [],
        "conflicts": []
      },
      "UnrestrictedEtherFlow": {
        "violations": [
          1345
        ],
        "warnings": [
          1027,
          1166,
          1175,
          1180,
          1218,
          1227,
          1269,
          1273,
          1277,
          1281,
          1292,
          1296,
          1298,
          1300,
          1315,
          1316,
          1318,
          1320,
          1332,
          1341,
          1344,
          1357,
          1358,
          1371,
          1382,
          1402,
          1414,
          1423,
          1424,
          1425,
          1427,
          1436,
          1437,
          1438,
          1439
        ],
        "safe": [
          1157,
          1215
        ],
        "conflicts": []
      },
      "UnrestrictedWrite": {
        "violations": [
          1302,
          1303,
          1307,
          1322,
          1415,
          1416,
          1417,
          1423,
          1424,
          1425,
          1428,
          1429,
          1430,
          1437,
          1438,
          1439
        ],
        "warnings": [
          1323,
          1348
        ],
        "safe": [
          1165,
          1174,
          1179,
          1219,
          1220,
          1221
        ],
        "conflicts": [
          203,
          514,
          520,
          1065,
          1071,
          1077,
          1087,
          1092,
          1098,
          1103,
          1108,
          1113,
          1119,
          1124,
          1129,
          1135,
          1142,
          1363,
          1372
        ]
      }
    },
    "securifyErrors": {
      "errors": []
    }
  },
  "/home/jion1/securify/smart_contract_source_code/22902.sol:ERC223Interface": {
    "results": {
      "DAO": {
        "violations": [],
        "warnings": [],
        "safe": [],
        "conflicts": []
      },
      "DAOConstantGas": {
        "violations": [],
        "warnings": [],
        "safe": [],
        "conflicts": []
      },
      "LockedEther": {
        "violations": [],
        "warnings": [
          -1
        ],
        "safe": [],
        "conflicts": []
      },
      "MissingInputValidation": {
        "violations": [],
        "warnings": [],
        "safe": [],
        "conflicts": []
      },
      "TODAmount": {
        "violations": [],
        "warnings": [],
        "safe": [],
        "conflicts": []
      },
      "TODReceiver": {
        "violations": [],
        "warnings": [],
        "safe": [],
        "conflicts": []
      },
      "UnhandledException": {
        "violations": [],
        "warnings": [],
        "safe": [],
        "conflicts": []
      },
      "UnrestrictedEtherFlow": {
        "violations": [],
        "warnings": [],
        "safe": [],
        "conflicts": []
      },
      "UnrestrictedWrite": {
        "violations": [],
        "warnings": [],
        "safe": [],
        "conflicts": []
      }
    },
    "securifyErrors": {
      "errors": [
        {
          "error": "mapping_error",
          "stackTrace": "ch.securify.MappingNotFoundException\n\tat ch.securify.CompilationHelpers.bytecodeOffsetToSourceOffset(CompilationHelpers.java:72)\n\tat ch.securify.CompilationHelpers.getMatchedLines(CompilationHelpers.java:126)\n\tat ch.securify.CompilationHelpers.getMappingsFromStatusFile(CompilationHelpers.java:154)\n\tat ch.securify.Main.processCompilationOutput(Main.java:129)\n\tat ch.securify.Main.processSolidityFile(Main.java:93)\n\tat ch.securify.Main.main(Main.java:230)\n"
        }
      ]
    }
  },
  "/home/jion1/securify/smart_contract_source_code/22902.sol:ERC223ReceivingContract": {
    "results": {
      "DAO": {
        "violations": [],
        "warnings": [],
        "safe": [],
        "conflicts": []
      },
      "DAOConstantGas": {
        "violations": [],
        "warnings": [],
        "safe": [],
        "conflicts": []
      },
      "LockedEther": {
        "violations": [],
        "warnings": [],
        "safe": [],
        "conflicts": [
          649
        ]
      },
      "MissingInputValidation": {
        "violations": [
          659
        ],
        "warnings": [
          649
        ],
        "safe": [],
        "conflicts": []
      },
      "TODAmount": {
        "violations": [],
        "warnings": [],
        "safe": [],
        "conflicts": []
      },
      "TODReceiver": {
        "violations": [],
        "warnings": [],
        "safe": [],
        "conflicts": []
      },
      "UnhandledException": {
        "violations": [],
        "warnings": [],
        "safe": [],
        "conflicts": []
      },
      "UnrestrictedEtherFlow": {
        "violations": [],
        "warnings": [],
        "safe": [],
        "conflicts": []
      },
      "UnrestrictedWrite": {
        "violations": [],
        "warnings": [],
        "safe": [],
        "conflicts": []
      }
    },
    "securifyErrors": {
      "errors": []
    }
  },
  "/home/jion1/securify/smart_contract_source_code/22902.sol:ETHPriceProvider": {
    "results": {
      "DAO": {
        "violations": [],
        "warnings": [],
        "safe": [],
        "conflicts": []
      },
      "DAOConstantGas": {
        "violations": [],
        "warnings": [],
        "safe": [],
        "conflicts": []
      },
      "LockedEther": {
        "violations": [],
        "warnings": [
          -1
        ],
        "safe": [],
        "conflicts": []
      },
      "MissingInputValidation": {
        "violations": [],
        "warnings": [],
        "safe": [],
        "conflicts": []
      },
      "TODAmount": {
        "violations": [],
        "warnings": [],
        "safe": [],
        "conflicts": []
      },
      "TODReceiver": {
        "violations": [],
        "warnings": [],
        "safe": [],
        "conflicts": []
      },
      "UnhandledException": {
        "violations": [],
        "warnings": [],
        "safe": [],
        "conflicts": []
      },
      "UnrestrictedEtherFlow": {
        "violations": [],
        "warnings": [],
        "safe": [],
        "conflicts": []
      },
      "UnrestrictedWrite": {
        "violations": [],
        "warnings": [],
        "safe": [],
        "conflicts": []
      }
    },
    "securifyErrors": {
      "errors": [
        {
          "error": "mapping_error",
          "stackTrace": "ch.securify.MappingNotFoundException\n\tat ch.securify.CompilationHelpers.bytecodeOffsetToSourceOffset(CompilationHelpers.java:72)\n\tat ch.securify.CompilationHelpers.getMatchedLines(CompilationHelpers.java:126)\n\tat ch.securify.CompilationHelpers.getMappingsFromStatusFile(CompilationHelpers.java:154)\n\tat ch.securify.Main.processCompilationOutput(Main.java:129)\n\tat ch.securify.Main.processSolidityFile(Main.java:93)\n\tat ch.securify.Main.main(Main.java:230)\n"
        }
      ]
    }
  },
  "/home/jion1/securify/smart_contract_source_code/22902.sol:ETHPriceWatcher": {
    "results": {
      "DAO": {
        "violations": [],
        "warnings": [],
        "safe": [],
        "conflicts": []
      },
      "DAOConstantGas": {
        "violations": [],
        "warnings": [],
        "safe": [],
        "conflicts": []
      },
      "LockedEther": {
        "violations": [],
        "warnings": [
          -1
        ],
        "safe": [],
        "conflicts": []
      },
      "MissingInputValidation": {
        "violations": [],
        "warnings": [],
        "safe": [],
        "conflicts": []
      },
      "TODAmount": {
        "violations": [],
        "warnings": [],
        "safe": [],
        "conflicts": []
      },
      "TODReceiver": {
        "violations": [],
        "warnings": [],
        "safe": [],
        "conflicts": []
      },
      "UnhandledException": {
        "violations": [],
        "warnings": [],
        "safe": [],
        "conflicts": []
      },
      "UnrestrictedEtherFlow": {
        "violations": [],
        "warnings": [],
        "safe": [],
        "conflicts": []
      },
      "UnrestrictedWrite": {
        "violations": [],
        "warnings": [],
        "safe": [],
        "conflicts": []
      }
    },
    "securifyErrors": {
      "errors": [
        {
          "error": "mapping_error",
          "stackTrace": "ch.securify.MappingNotFoundException\n\tat ch.securify.CompilationHelpers.bytecodeOffsetToSourceOffset(CompilationHelpers.java:72)\n\tat ch.securify.CompilationHelpers.getMatchedLines(CompilationHelpers.java:126)\n\tat ch.securify.CompilationHelpers.getMappingsFromStatusFile(CompilationHelpers.java:154)\n\tat ch.securify.Main.processCompilationOutput(Main.java:129)\n\tat ch.securify.Main.processSolidityFile(Main.java:93)\n\tat ch.securify.Main.main(Main.java:230)\n"
        }
      ]
    }
  },
  "/home/jion1/securify/smart_contract_source_code/22902.sol:Hold": {
    "results": {
      "DAO": {
        "violations": [],
        "warnings": [],
        "safe": [],
        "conflicts": []
      },
      "DAOConstantGas": {
        "violations": [
          876,
          884,
          932
        ],
        "warnings": [
          915
        ],
        "safe": [
          876
        ],
        "conflicts": []
      },
      "LockedEther": {
        "violations": [],
        "warnings": [
          813
        ],
        "safe": [],
        "conflicts": []
      },
      "MissingInputValidation": {
        "violations": [
          867,
          945
        ],
        "warnings": [
          183,
          200,
          816,
          817,
          818,
          819,
          821,
          824,
          826,
          857,
          862,
          872,
          889,
          893,
          901,
          908,
          912
        ],
        "safe": [
          881,
          919
        ],
        "conflicts": []
      },
      "TODAmount": {
        "violations": [
          915,
          932
        ],
        "warnings": [],
        "safe": [
          876,
          884
        ],
        "conflicts": []
      },
      "TODReceiver": {
        "violations": [
          915
        ],
        "warnings": [
          932
        ],
        "safe": [
          876,
          884
        ],
        "conflicts": []
      },
      "UnhandledException": {
        "violations": [],
        "warnings": [
          837,
          876,
          884,
          915,
          924,
          929,
          932
        ],
        "safe": [],
        "conflicts": []
      },
      "UnrestrictedEtherFlow": {
        "violations": [],
        "warnings": [
          837,
          915,
          924,
          929
        ],
        "safe": [
          876,
          884,
          932
        ],
        "conflicts": []
      },
      "UnrestrictedWrite": {
        "violations": [
          868,
          877,
          885,
          934,
          936
        ],
        "warnings": [],
        "safe": [
          877
        ],
        "conflicts": [
          203,
          859,
          864,
          896,
          904
        ]
      }
    },
    "securifyErrors": {
      "errors": []
    }
  },
  "/home/jion1/securify/smart_contract_source_code/22902.sol:OraclizeAddrResolverI": {
    "results": {
      "DAO": {
        "violations": [],
        "warnings": [],
        "safe": [],
        "conflicts": []
      },
      "DAOConstantGas": {
        "violations": [],
        "warnings": [],
        "safe": [],
        "conflicts": []
      },
      "LockedEther": {
        "violations": [],
        "warnings": [
          -1
        ],
        "safe": [],
        "conflicts": []
      },
      "MissingInputValidation": {
        "violations": [],
        "warnings": [],
        "safe": [],
        "conflicts": []
      },
      "TODAmount": {
        "violations": [],
        "warnings": [],
        "safe": [],
        "conflicts": []
      },
      "TODReceiver": {
        "violations": [],
        "warnings": [],
        "safe": [],
        "conflicts": []
      },
      "UnhandledException": {
        "violations": [],
        "warnings": [],
        "safe": [],
        "conflicts": []
      },
      "UnrestrictedEtherFlow": {
        "violations": [],
        "warnings": [],
        "safe": [],
        "conflicts": []
      },
      "UnrestrictedWrite": {
        "violations": [],
        "warnings": [],
        "safe": [],
        "conflicts": []
      }
    },
    "securifyErrors": {
      "errors": [
        {
          "error": "mapping_error",
          "stackTrace": "ch.securify.MappingNotFoundException\n\tat ch.securify.CompilationHelpers.bytecodeOffsetToSourceOffset(CompilationHelpers.java:72)\n\tat ch.securify.CompilationHelpers.getMatchedLines(CompilationHelpers.java:126)\n\tat ch.securify.CompilationHelpers.getMappingsFromStatusFile(CompilationHelpers.java:154)\n\tat ch.securify.Main.processCompilationOutput(Main.java:129)\n\tat ch.securify.Main.processSolidityFile(Main.java:93)\n\tat ch.securify.Main.main(Main.java:230)\n"
        }
      ]
    }
  },
  "/home/jion1/securify/smart_contract_source_code/22902.sol:OraclizeC": {
    "results": {
      "DAO": {
        "violations": [],
        "warnings": [],
        "safe": [],
        "conflicts": []
      },
      "DAOConstantGas": {
        "violations": [],
        "warnings": [
          488
        ],
        "safe": [],
        "conflicts": []
      },
      "LockedEther": {
        "violations": [],
        "warnings": [
          430
        ],
        "safe": [],
        "conflicts": []
      },
      "MissingInputValidation": {
        "violations": [],
        "warnings": [],
        "safe": [],
        "conflicts": []
      },
      "TODAmount": {
        "violations": [
          488
        ],
        "warnings": [],
        "safe": [],
        "conflicts": []
      },
      "TODReceiver": {
        "violations": [],
        "warnings": [
          488
        ],
        "safe": [],
        "conflicts": []
      },
      "UnhandledException": {
        "violations": [],
        "warnings": [
          56,
          57,
          136,
          488
        ],
        "safe": [],
        "conflicts": []
      },
      "UnrestrictedEtherFlow": {
        "violations": [],
        "warnings": [
          56,
          57,
          136,
          488
        ],
        "safe": [],
        "conflicts": []
      },
      "UnrestrictedWrite": {
        "violations": [
          430
        ],
        "warnings": [],
        "safe": [],
        "conflicts": [
          57,
          72,
          77,
          82,
          87,
          92,
          96,
          100,
          203,
          430,
          460,
          470,
          481
        ]
      }
    },
    "securifyErrors": {
      "errors": []
    }
  },
  "/home/jion1/securify/smart_contract_source_code/22902.sol:OraclizeI": {
    "results": {
      "DAO": {
        "violations": [],
        "warnings": [],
        "safe": [],
        "conflicts": []
      },
      "DAOConstantGas": {
        "violations": [],
        "warnings": [],
        "safe": [],
        "conflicts": []
      },
      "LockedEther": {
        "violations": [],
        "warnings": [
          -1
        ],
        "safe": [],
        "conflicts": []
      },
      "MissingInputValidation": {
        "violations": [],
        "warnings": [],
        "safe": [],
        "conflicts": []
      },
      "TODAmount": {
        "violations": [],
        "warnings": [],
        "safe": [],
        "conflicts": []
      },
      "TODReceiver": {
        "violations": [],
        "warnings": [],
        "safe": [],
        "conflicts": []
      },
      "UnhandledException": {
        "violations": [],
        "warnings": [],
        "safe": [],
        "conflicts": []
      },
      "UnrestrictedEtherFlow": {
        "violations": [],
        "warnings": [],
        "safe": [],
        "conflicts": []
      },
      "UnrestrictedWrite": {
        "violations": [],
        "warnings": [],
        "safe": [],
        "conflicts": []
      }
    },
    "securifyErrors": {
      "errors": [
        {
          "error": "mapping_error",
          "stackTrace": "ch.securify.MappingNotFoundException\n\tat ch.securify.CompilationHelpers.bytecodeOffsetToSourceOffset(CompilationHelpers.java:72)\n\tat ch.securify.CompilationHelpers.getMatchedLines(CompilationHelpers.java:126)\n\tat ch.securify.CompilationHelpers.getMappingsFromStatusFile(CompilationHelpers.java:154)\n\tat ch.securify.Main.processCompilationOutput(Main.java:129)\n\tat ch.securify.Main.processSolidityFile(Main.java:93)\n\tat ch.securify.Main.main(Main.java:230)\n"
        }
      ]
    }
  },
  "/home/jion1/securify/smart_contract_source_code/22902.sol:Ownable": {
    "results": {
      "DAO": {
        "violations": [],
        "warnings": [],
        "safe": [],
        "conflicts": []
      },
      "DAOConstantGas": {
        "violations": [],
        "warnings": [],
        "safe": [],
        "conflicts": []
      },
      "LockedEther": {
        "violations": [],
        "warnings": [],
        "safe": [],
        "conflicts": [
          182
        ]
      },
      "MissingInputValidation": {
        "violations": [],
        "warnings": [
          183,
          200
        ],
        "safe": [],
        "conflicts": []
      },
      "TODAmount": {
        "violations": [],
        "warnings": [],
        "safe": [],
        "conflicts": []
      },
      "TODReceiver": {
        "violations": [],
        "warnings": [],
        "safe": [],
        "conflicts": []
      },
      "UnhandledException": {
        "violations": [],
        "warnings": [],
        "safe": [],
        "conflicts": []
      },
      "UnrestrictedEtherFlow": {
        "violations": [],
        "warnings": [],
        "safe": [],
        "conflicts": []
      },
      "UnrestrictedWrite": {
        "violations": [],
        "warnings": [],
        "safe": [],
        "conflicts": [
          203
        ]
      }
    },
    "securifyErrors": {
      "errors": []
    }
  },
  "/home/jion1/securify/smart_contract_source_code/22902.sol:Pausable": {
    "results": {
      "DAO": {
        "violations": [],
        "warnings": [],
        "safe": [],
        "conflicts": []
      },
      "DAOConstantGas": {
        "violations": [],
        "warnings": [],
        "safe": [],
        "conflicts": []
      },
      "LockedEther": {
        "violations": [],
        "warnings": [],
        "safe": [],
        "conflicts": [
          493
        ]
      },
      "MissingInputValidation": {
        "violations": [],
        "warnings": [
          183,
          200,
          497,
          513,
          519
        ],
        "safe": [],
        "conflicts": []
      },
      "TODAmount": {
        "violations": [],
        "warnings": [],
        "safe": [],
        "conflicts": []
      },
      "TODReceiver": {
        "violations": [],
        "warnings": [],
        "safe": [],
        "conflicts": []
      },
      "UnhandledException": {
        "violations": [],
        "warnings": [],
        "safe": [],
        "conflicts": []
      },
      "UnrestrictedEtherFlow": {
        "violations": [],
        "warnings": [],
        "safe": [],
        "conflicts": []
      },
      "UnrestrictedWrite": {
        "violations": [],
        "warnings": [],
        "safe": [],
        "conflicts": [
          203,
          514,
          520
        ]
      }
    },
    "securifyErrors": {
      "errors": []
    }
  },
  "/home/jion1/securify/smart_contract_source_code/22902.sol:PermissionManager": {
    "results": {
      "DAO": {
        "violations": [],
        "warnings": [],
        "safe": [],
        "conflicts": []
      },
      "DAOConstantGas": {
        "violations": [],
        "warnings": [],
        "safe": [],
        "conflicts": []
      },
      "LockedEther": {
        "violations": [],
        "warnings": [],
        "safe": [],
        "conflicts": [
          282
        ]
      },
      "MissingInputValidation": {
        "violations": [
          285,
          289,
          293
        ],
        "warnings": [
          183,
          200
        ],
        "safe": [],
        "conflicts": []
      },
      "TODAmount": {
        "violations": [],
        "warnings": [],
        "safe": [],
        "conflicts": []
      },
      "TODReceiver": {
        "violations": [],
        "warnings": [],
        "safe": [],
        "conflicts": []
      },
      "UnhandledException": {
        "violations": [],
        "warnings": [],
        "safe": [],
        "conflicts": []
      },
      "UnrestrictedEtherFlow": {
        "violations": [],
        "warnings": [],
        "safe": [],
        "conflicts": []
      },
      "UnrestrictedWrite": {
        "violations": [],
        "warnings": [],
        "safe": [],
        "conflicts": [
          203,
          286,
          290
        ]
      }
    },
    "securifyErrors": {
      "errors": []
    }
  },
  "/home/jion1/securify/smart_contract_source_code/22902.sol:Registry": {
    "results": {
      "DAO": {
        "violations": [],
        "warnings": [],
        "safe": [],
        "conflicts": []
      },
      "DAOConstantGas": {
        "violations": [],
        "warnings": [],
        "safe": [],
        "conflicts": []
      },
      "LockedEther": {
        "violations": [],
        "warnings": [],
        "safe": [],
        "conflicts": [
          301
        ]
      },
      "MissingInputValidation": {
        "violations": [
          311,
          338,
          342,
          346,
          350,
          370,
          380,
          392,
          396,
          400,
          404,
          408,
          419
        ],
        "warnings": [
          183,
          200,
          317,
          319,
          333,
          423
        ],
        "safe": [],
        "conflicts": []
      },
      "TODAmount": {
        "violations": [],
        "warnings": [],
        "safe": [],
        "conflicts": []
      },
      "TODReceiver": {
        "violations": [],
        "warnings": [],
        "safe": [],
        "conflicts": []
      },
      "UnhandledException": {
        "violations": [],
        "warnings": [
          322
        ],
        "safe": [],
        "conflicts": []
      },
      "UnrestrictedEtherFlow": {
        "violations": [],
        "warnings": [
          322
        ],
        "safe": [],
        "conflicts": []
      },
      "UnrestrictedWrite": {
        "violations": [
          343,
          347,
          353,
          354,
          355,
          356,
          357,
          359,
          360,
          362,
          363,
          364,
          365,
          372,
          373,
          374,
          375,
          381,
          382,
          383,
          384,
          385,
          386,
          387,
          410,
          411,
          412,
          413,
          415
        ],
        "warnings": [],
        "safe": [],
        "conflicts": [
          203,
          335
        ]
      }
    },
    "securifyErrors": {
      "errors": []
    }
  },
  "/home/jion1/securify/smart_contract_source_code/22902.sol:SafeMath": {
    "results": {},
    "securifyErrors": {
      "errors": [
        {
          "error": "decompilation_error",
          "stackTrace": "java.util.EmptyStackException\n\tat java.util.Stack.peek(Stack.java:102)\n\tat java.util.Stack.pop(Stack.java:84)\n\tat ch.securify.decompiler.Variable.takeFromStack(Variable.java:83)\n\tat ch.securify.decompiler.InstructionFactory.createAndApply(InstructionFactory.java:92)\n\tat ch.securify.decompiler.DecompilerFallback.decompile(DecompilerFallback.java:111)\n\tat ch.securify.Main.decompileContract(Main.java:274)\n\tat ch.securify.Main.processHexFile(Main.java:158)\n\tat ch.securify.Main.processCompilationOutput(Main.java:121)\n\tat ch.securify.Main.processSolidityFile(Main.java:93)\n\tat ch.securify.Main.main(Main.java:230)\n"
        }
      ]
    }
  },
  "/home/jion1/securify/smart_contract_source_code/22902.sol:UnityToken": {
    "results": {
      "DAO": {
        "violations": [],
        "warnings": [],
        "safe": [],
        "conflicts": []
      },
      "DAOConstantGas": {
        "violations": [],
        "warnings": [],
        "safe": [],
        "conflicts": []
      },
      "LockedEther": {
        "violations": [],
        "warnings": [],
        "safe": [],
        "conflicts": [
          690
        ]
      },
      "MissingInputValidation": {
        "violations": [],
        "warnings": [],
        "safe": [],
        "conflicts": []
      },
      "TODAmount": {
        "violations": [],
        "warnings": [],
        "safe": [],
        "conflicts": []
      },
      "TODReceiver": {
        "violations": [],
        "warnings": [],
        "safe": [],
        "conflicts": []
      },
      "UnhandledException": {
        "violations": [],
        "warnings": [
          739,
          797
        ],
        "safe": [],
        "conflicts": []
      },
      "UnrestrictedEtherFlow": {
        "violations": [],
        "warnings": [
          739,
          797
        ],
        "safe": [],
        "conflicts": []
      },
      "UnrestrictedWrite": {
        "violations": [],
        "warnings": [
          737,
          783,
          794
        ],
        "safe": [
          738,
          784,
          795
        ],
        "conflicts": [
          710,
          714
        ]
      }
    },
    "securifyErrors": {
      "errors": []
    }
  },
  "/home/jion1/securify/smart_contract_source_code/22902.sol:usingOraclize": {
    "results": {
      "DAO": {
        "violations": [],
        "warnings": [],
        "safe": [],
        "conflicts": []
      },
      "DAOConstantGas": {
        "violations": [],
        "warnings": [],
        "safe": [],
        "conflicts": []
      },
      "LockedEther": {
        "violations": [],
        "warnings": [
          33
        ],
        "safe": [],
        "conflicts": []
      },
      "MissingInputValidation": {
        "violations": [],
        "warnings": [],
        "safe": [],
        "conflicts": []
      },
      "TODAmount": {
        "violations": [],
        "warnings": [],
        "safe": [],
        "conflicts": []
      },
      "TODReceiver": {
        "violations": [],
        "warnings": [],
        "safe": [],
        "conflicts": []
      },
      "UnhandledException": {
        "violations": [],
        "warnings": [],
        "safe": [],
        "conflicts": []
      },
      "UnrestrictedEtherFlow": {
        "violations": [],
        "warnings": [],
        "safe": [],
        "conflicts": []
      },
      "UnrestrictedWrite": {
        "violations": [],
        "warnings": [],
        "safe": [],
        "conflicts": []
      }
    },
    "securifyErrors": {
      "errors": []
    }
  }
}